datahub_semantic_agent.cpython-311-aarch64-linux-musl.so
datahub_semantic_agent.cpython-312-aarch64-linux-musl.so
datahub_semantic_agent.pyi
datahub_semantic_agent/list_queries.gql
datahub_semantic_agent/py.typed
datahub_semantic_agent.build/.gitignore
datahub_semantic_agent-0.1.3.dist-info/METADATA
datahub_semantic_agent-0.1.3.dist-info/WHEEL
datahub_semantic_agent-0.1.3.dist-info/entry_points.txt
datahub_semantic_agent-0.1.3.dist-info/top_level.txt
datahub_semantic_agent-0.1.3.dist-info/RECORD
