Metadata-Version: 2.4
Name: datahub-semantic-agent
Version: 0.1.3
Summary: MCP server for talking to your data, powered by DataHub
Author-email: Harshal Sheth <harshal@datahub.com>
Requires-Python: >=3.11
Requires-Dist: acryl-datahub-cloud>=0.3.12
Requires-Dist: acryl-datahub[snowflake-slim,sql-parser]>=1.1.0.3
Requires-Dist: diskcache>=5.6.3
Requires-Dist: instructor>=1.9.0
Requires-Dist: litellm>=1.73.1
Requires-Dist: loguru>=0.7.3
Requires-Dist: fastmcp>=2.0.0
Requires-Dist: mlflow-skinny>=3.1.0
Requires-Dist: pydantic>=2.11
Requires-Dist: pydantic-settings>=2.6.0
Requires-Dist: pyyaml>=6.0.2
Requires-Dist: snowflake-connector-python==3.16.0
